mcp_kicad_sch_api/__init__.py
mcp_kicad_sch_api/__main__.py
mcp_kicad_sch_api/server.py
mcp_kicad_sch_api-0.1.7.dist-info/licenses/LICENSE
mcp_kicad_sch_api-0.1.7.dist-info/METADATA
mcp_kicad_sch_api-0.1.7.dist-info/WHEEL
mcp_kicad_sch_api-0.1.7.dist-info/entry_points.txt
mcp_kicad_sch_api-0.1.7.dist-info/top_level.txt
mcp_kicad_sch_api-0.1.7.dist-info/RECORD
