Metadata-Version: 2.4
Name: mcp-kicad-sch-api
Version: 0.1.7
Summary: Model Context Protocol server for KiCAD schematic manipulation
Author-email: Circuit-Synth <shane@circuit-synth.com>
Maintainer-email: Circuit-Synth <shane@circuit-synth.com>
License-Expression: MIT
Project-URL: Homepage, https://github.com/circuit-synth/mcp-kicad-sch-api
Project-URL: Documentation, https://circuit-synth.github.io/mcp-kicad-sch-api/
Project-URL: Repository, https://github.com/circuit-synth/mcp-kicad-sch-api.git
Project-URL: Bug Reports, https://github.com/circuit-synth/mcp-kicad-sch-api/issues
Project-URL: Changelog, https://github.com/circuit-synth/mcp-kicad-sch-api/blob/main/CHANGELOG.md
Keywords: mcp,kicad,schematic,eda,electronics,circuit-design,ai,model-context-protocol,llm,agent
Classifier: Development Status :: 4 - Beta
Classifier: Intended Audience :: Developers
Classifier: Intended Audience :: Science/Research
Classifier: Topic :: Scientific/Engineering :: Electronic Design Automation (EDA)
Classifier: Topic :: Software Development :: Libraries :: Python Modules
Classifier: Programming Language :: Python :: 3
Classifier: Programming Language :: Python :: 3.10
Classifier: Programming Language :: Python :: 3.11
Classifier: Programming Language :: Python :: 3.12
Classifier: Programming Language :: Python :: 3.13
Classifier: Operating System :: OS Independent
Requires-Python: >=3.10
License-File: LICENSE
Requires-Dist: click>=8.1.7
Requires-Dist: mcp>=1.0.0
Requires-Dist: kicad-sch-api>=0.1.7
Provides-Extra: dev
Requires-Dist: pytest>=7.0.0; extra == "dev"
Requires-Dist: pytest-asyncio>=0.21.0; extra == "dev"
Requires-Dist: pytest-cov>=4.0.0; extra == "dev"
Requires-Dist: black>=22.0.0; extra == "dev"
Requires-Dist: isort>=5.0.0; extra == "dev"
Requires-Dist: flake8>=4.0.0; extra == "dev"
Requires-Dist: mypy>=1.0.0; extra == "dev"
Dynamic: license-file
